client/__init__.py
client/client3.py
client/metaclasses.py
client/client/__init__.py
client/client/add_contact.py
client/client/client_db_decl.py
client/client/del_contact.py
client/client/main_window.py
client/client/main_window_conv.py
client/client/start_dialog.py
client/client/transport.py
client/common/__init__.py
client/common/decorator.py
client/common/descriptrs.py
client/common/errors.py
client/common/utils.py
client/common/veriables.py
client/logs/__init__.py
client/logs/config_client_log.py
client/logs/config_server_log.py
client_mess-0.1.1.dist-info/METADATA
client_mess-0.1.1.dist-info/WHEEL
client_mess-0.1.1.dist-info/top_level.txt
client_mess-0.1.1.dist-info/RECORD
